numpy_camera/__init__.py
numpy_camera/pinhole_camera.py
numpy_camera/threaded_camera.py
numpy_camera-0.0.1.dist-info/LICENSE
numpy_camera-0.0.1.dist-info/WHEEL
numpy_camera-0.0.1.dist-info/METADATA
numpy_camera-0.0.1.dist-info/RECORD
